{
  "bullet": {
    "type": "hyperlaser",
    "damage": "0",
    "weight":"0",
    "spread": "0",
    "piercing": "2147483647",
    "dist": "400",
    "texture": {
      "texture": "effects/blue_hyperlaser",
      "layer": "3",
      "lifetime": "20",
      "width": "0.5"
    }
  },
  "projectiles": "1",
  "maxBullets": "6",
  "fireRate": "30",
  "reloadRate": "2",
  "knockBack": "0.01",
  "rumble": "0.5",
  "recoilMult": "0.2",
  "minRecoil": "0",
  "speed": "6.28318530718",
  "sound": {
    "fire": "guns/lever_rifle/lever_rifle_fire.mp3",
    "empty": "guns/lever_rifle/lever_rifle_empty.mp3",
    "reload": "guns/lever_rifle/lever_rifle_reload.mp3"
  },
  "effect": {
    "texture": "missing_texture",
    "size": "0"
  },
  "gun": {
    "texture": "guns/blue_hyperlaser",
    "width": "1",
    "height": "0.55",
    "xOffset": "-0.5",
    "yOffset": "0.2"
  }
}
